{
    "PackedTextures": [
        {
            "TextureName": "tex 1 - doggy_texture0_layer0.png",
            "Layer": 0,
            "PackedDrawables": [
                {
                    "Name": "Panties",
                    "RectInt": {
                        "x": 5,
                        "y": 5,
                        "width": 256,
                        "height": 240
                    },
                    "ColorIndex": 0,
                    "DrawableType": 0,
                    "BypassColorScaler": false
                }
            ],
            "Targets": [
                "doggy"
            ],
            "DontIncludeVanillaLayers": false
        }
    ]
}